paddle2onnx/__init__.py
paddle2onnx/command.py
paddle2onnx/convert.py
paddle2onnx/paddle2onnx_cpp2py_export.cpython-37m-x86_64-linux-gnu.so
paddle2onnx/utils.py
paddle2onnx/version.py
paddle2onnx/constant/__init__.py
paddle2onnx/constant/constant.py
paddle2onnx/constant/dtypes.py
paddle2onnx/constant/op_mapping_status.py
paddle2onnx/graph/__init__.py
paddle2onnx/graph/dygraph_helper.py
paddle2onnx/graph/graph.py
paddle2onnx/graph/graph_helper.py
paddle2onnx/graph/onnx_graph.py
paddle2onnx/graph/paddle_graph.py
paddle2onnx/op_mapper/__init__.py
paddle2onnx/op_mapper/activation.py
paddle2onnx/op_mapper/logic.py
paddle2onnx/op_mapper/mapper_helper.py
paddle2onnx/op_mapper/math.py
paddle2onnx/op_mapper/nn.py
paddle2onnx/op_mapper/op_mapper.py
paddle2onnx/op_mapper/search.py
paddle2onnx/op_mapper/tensor.py
paddle2onnx/op_mapper/custom_paddle_op/__init__.py
paddle2onnx/op_mapper/custom_paddle_op/anchor_generator.py
paddle2onnx/op_mapper/custom_paddle_op/box_clip.py
paddle2onnx/op_mapper/custom_paddle_op/collect_fpn_proposals.py
paddle2onnx/op_mapper/custom_paddle_op/deformable_conv.py
paddle2onnx/op_mapper/custom_paddle_op/distribute_fpn_proposals.py
paddle2onnx/op_mapper/custom_paddle_op/generate_proposals.py
paddle2onnx/op_mapper/custom_paddle_op/grid_sampler.py
paddle2onnx/op_mapper/detection/__init__.py
paddle2onnx/op_mapper/detection/box_coder.py
paddle2onnx/op_mapper/detection/density_prior_box.py
paddle2onnx/op_mapper/detection/multiclass_nms.py
paddle2onnx/op_mapper/detection/prior_box.py
paddle2onnx/op_mapper/detection/yolo_box.py
paddle2onnx/op_mapper/sequence/__init__.py
paddle2onnx/op_mapper/sequence/im2sequence.py
paddle2onnx/passes/__init__.py
paddle2onnx/passes/dumplicate_names_pass.py
paddle2onnx/passes/inplace_node_pass.py
paddle2onnx/passes/pass_manager.py
paddle2onnx1-0.2.0.dist-info/LICENSE
paddle2onnx1-0.2.0.dist-info/METADATA
paddle2onnx1-0.2.0.dist-info/WHEEL
paddle2onnx1-0.2.0.dist-info/entry_points.txt
paddle2onnx1-0.2.0.dist-info/top_level.txt
paddle2onnx1-0.2.0.dist-info/RECORD
